float_table/__init__.py
float_table/fmt.py
float_table-0.1.8.dist-info/METADATA
float_table-0.1.8.dist-info/WHEEL
float_table-0.1.8.dist-info/RECORD
