Metadata-Version: 2.1
Name: float-table
Version: 0.1.8
Summary: Top-level package for float-table.
Home-page: https://github.com/tadamcz/float-table
Author: Tom Adamczewski
Author-email: tadamczewskipublic@gmail.com
Requires-Python: >=3.8,<4
Classifier: Natural Language :: English
Classifier: Programming Language :: Python :: 3
Classifier: Programming Language :: Python :: 3.8
Classifier: Programming Language :: Python :: 3.9
Classifier: Programming Language :: Python :: 3.10
Classifier: Programming Language :: Python :: 3.11
Requires-Dist: numpy (>=1,<2)
Requires-Dist: pandas (>=2,<3)
Requires-Dist: tabulate (>=0.9.0,<0.10.0)
